helloworld_clippersys.py
helloworld_clippersys-0.0.2.dist-info/LICENSE.txt
helloworld_clippersys-0.0.2.dist-info/METADATA
helloworld_clippersys-0.0.2.dist-info/WHEEL
helloworld_clippersys-0.0.2.dist-info/top_level.txt
helloworld_clippersys-0.0.2.dist-info/RECORD
